speechscore/__init__.py
speechscore/app.py
speechscore/cli.py
speechscore-0.0.1.dist-info/LICENSE.txt
speechscore-0.0.1.dist-info/METADATA
speechscore-0.0.1.dist-info/WHEEL
speechscore-0.0.1.dist-info/entry_points.txt
speechscore-0.0.1.dist-info/RECORD
