Metadata-Version: 2.3
Name: speechscore
Version: 0.0.1
Summary: speechscore is a Python package for benchmarking models on speech perception behavioral and neural data.
License: Apache-2.0
Keywords: python,package,template
Author: gelbanna
Author-email: gelbanna@mit.edu
Maintainer: gelbanna
Maintainer-email: gelbanna@mit.edu
Requires-Python: >=3.10,<3.13
Classifier: Development Status :: 3 - Alpha
Classifier: Programming Language :: Python :: 3.10
Classifier: License :: OSI Approved :: Apache Software License
Classifier: Operating System :: OS Independent
Requires-Dist: click (>=8.2,<9.0)
